{"department": "Department of Applied Mechanics", "name": "APL331 Advanced Mechanics of Solids", "description": "Mathematical Preliminaries (scalar, vector, tensor operation) Thermodynamics thermodynamically framework for constitutive modeling), Kinematics of Deformation & Motion, Stress-strain principles, Elasticity, Anisotropy, viscoelasticity, multi-physical coupling effect, plasticity, viscoelasticity. Experimental: Experimental characterization, data analysis, Model fitting.", "credits": "3 (3-0-0)", "pre": "APL104/APL105/APL108 EC50"}